ua_redmine_api/__init__.py
ua_redmine_api/ua_redmine_api.py
ua_redmine_api-1.0.7.dist-info/LICENSE
ua_redmine_api-1.0.7.dist-info/METADATA
ua_redmine_api-1.0.7.dist-info/WHEEL
ua_redmine_api-1.0.7.dist-info/top_level.txt
ua_redmine_api-1.0.7.dist-info/RECORD
