Metadata-Version: 2.1
Name: ua-redmine-api
Version: 1.0.7
Summary: Provides easy interface for making REST requests to University of Arizona RII Redmine database.
Home-page: https://github.com/UACoreFacilitiesIT/UA-Redmine-API
Author: Ryan Johannes-Bland
Author-email: rjjohannesbland@email.arizona.edu
License: MIT
Platform: UNKNOWN
Requires-Dist: requests
